omc_jmx/__init__.py
omc_jmx/jmx/__init__.py
omc_jmx/jmx/jmx.py
omc_jmx/jmx/bean/__init__.py
omc_jmx/jmx/bean/bean.py
omc_jmx/lib/__init__.py
omc_jmx/lib/jmxterm-1.0.2-uber.jar
omc_jmx/lib/__pycache__/__init__.cpython-37.pyc
omc_jmx/utils/__init__.py
omc_jmx-0.0.2.dist-info/METADATA
omc_jmx-0.0.2.dist-info/WHEEL
omc_jmx-0.0.2.dist-info/top_level.txt
omc_jmx-0.0.2.dist-info/RECORD
