Metadata-Version: 2.1
Name: omc-jmx
Version: 0.0.2
Summary: jmx plugin for omc
Home-page: https://github.com/linewx/omc-jmx
Author: Lu Ganlin
Author-email: linewx1981@gmail.com
License: MIT
Platform: UNKNOWN
Requires-Dist: omc (>=0.2.1)
